ewha_congestions/__init__ .py
ewha_congestions/three_congestions.py
ewha_congestions-0.2.0.dist-info/METADATA
ewha_congestions-0.2.0.dist-info/WHEEL
ewha_congestions-0.2.0.dist-info/top_level.txt
ewha_congestions-0.2.0.dist-info/RECORD
