Metadata-Version: 2.4
Name: ewha_congestions
Version: 0.2.0
Summary: A Python module for calculating and analyzing three types of congestion—Road, PM, and Pedestrian congestion.
Author-email: Jiyoon Lee <0197black@gmail.com>
Requires-Python: >=3.8
Requires-Dist: numpy
Requires-Dist: pandas
Requires-Dist: geopandas
Requires-Dist: movingpandas
Requires-Dist: tqdm
Requires-Dist: shapely
Requires-Dist: geopy
